paintedlife/__init__.py
paintedlife/game_of_life.py
paintedlife/pattern_generator.py
paintedlife/patterns.py
paintedlife-0.0.3.dist-info/LICENSE.txt
paintedlife-0.0.3.dist-info/METADATA
paintedlife-0.0.3.dist-info/WHEEL
paintedlife-0.0.3.dist-info/top_level.txt
paintedlife-0.0.3.dist-info/RECORD
