Metadata-Version: 2.1
Name: paintedlife
Version: 0.0.3
Summary: Conway's Game of Life, napari style (paintbrush inc.)
Home-page: https://github.com/abigailmcgovern/paintedlife
Author: Abigail S. McGovern
Author-email: abigail_mcgovern@hotmail.com
License: LICENSE.md
Platform: UNKNOWN
Classifier: Programming Language :: Python
Classifier: Programming Language :: Python :: 3 :: Only
Requires-Python: >=3.6
Requires-Dist: scipy
Requires-Dist: numpy
Requires-Dist: napari[all]
Requires-Dist: magicgui (==0.1.6)
